LICENSE
MANIFEST.in
README.md
setup.py
JSON2Mantle.egg-info/PKG-INFO
JSON2Mantle.egg-info/SOURCES.txt
JSON2Mantle.egg-info/dependency_links.txt
JSON2Mantle.egg-info/entry_points.txt
JSON2Mantle.egg-info/not-zip-safe
JSON2Mantle.egg-info/top_level.txt
json2mantle/__init__.py
json2mantle/cli.py
json2mantle/objc_template.py
json2mantle/renderer.py
json2mantle/utils.py
json2mantle/templates/model.h
json2mantle/templates/model.m