Metadata-Version: 1.1
Name: JSON2Mantle
Version: 0.0.8
Summary: Generate Mantle models using JSON files
Home-page: https://github.com/sutar/JSON2Mantle
Author: Xin Wang
Author-email: i@wangx.in
License: MIT
Keywords: mantle parser objective-c
Platform: UNKNOWN
Classifier: Development Status :: 4 - Beta
Classifier: License :: OSI Approved :: MIT License
Classifier: Intended Audience :: Developers
Classifier: Programming Language :: Python :: 2.7
Classifier: Programming Language :: Python :: 3.4
Classifier: Programming Language :: Objective C
Classifier: Topic :: Text Processing
